<annotation>
	<folder>smoke0</folder>
	<filename>000210.jpg</filename>
	<path>C:\Users\ZHANGYANJUN0810\Desktop\smoke0\000210.jpg</path>
	<source>
		<database>Unknown</database>
	</source>
	<size>
		<width>439</width>
		<height>600</height>
		<depth>3</depth>
	</size>
	<segmented>0</segmented>
	<object>
		<name>smoke</name>
		<pose>Unspecified</pose>
		<truncated>0</truncated>
		<difficult>0</difficult>
		<bndbox>
			<xmin>2</xmin>
			<ymin>192</ymin>
			<xmax>42</xmax>
			<ymax>222</ymax>
		</bndbox>
	</object>
	<object>
		<name>smoke</name>
		<pose>Unspecified</pose>
		<truncated>0</truncated>
		<difficult>0</difficult>
		<bndbox>
			<xmin>9</xmin>
			<ymin>550</ymin>
			<xmax>49</xmax>
			<ymax>592</ymax>
		</bndbox>
	</object>
</annotation>
