<annotation>
	<folder>smoke(0-499)</folder>
	<filename>000012.jpg</filename>
	<path>C:\Users\renbei\Documents\Tencent Files\1310293107\FileRecv\MobileFile\smoke(0-499)\smoke(0-499)\000012.jpg</path>
	<source>
		<database>Unknown</database>
	</source>
	<size>
		<width>1200</width>
		<height>800</height>
		<depth>3</depth>
	</size>
	<segmented>0</segmented>
	<object>
		<name>000012</name>
		<pose>Unspecified</pose>
		<truncated>0</truncated>
		<difficult>0</difficult>
		<bndbox>
			<xmin>730</xmin>
			<ymin>369</ymin>
			<xmax>758</xmax>
			<ymax>381</ymax>
		</bndbox>
	</object>
</annotation>
