<annotation>
	<folder>smoke(1600-2099)</folder>
	<filename>001916.jpg</filename>
	<path>C:\Users\Administrator\Desktop\新建文件夹 (2)\smoke(1600-2099)\001916.jpg</path>
	<source>
		<database>Unknown</database>
	</source>
	<size>
		<width>2248</width>
		<height>1080</height>
		<depth>3</depth>
	</size>
	<segmented>0</segmented>
	<object>
		<name>smoke</name>
		<pose>Unspecified</pose>
		<truncated>0</truncated>
		<difficult>0</difficult>
		<bndbox>
			<xmin>391</xmin>
			<ymin>403</ymin>
			<xmax>445</xmax>
			<ymax>462</ymax>
		</bndbox>
	</object>
	<object>
		<name>smoke</name>
		<pose>Unspecified</pose>
		<truncated>0</truncated>
		<difficult>0</difficult>
		<bndbox>
			<xmin>626</xmin>
			<ymin>562</ymin>
			<xmax>672</xmax>
			<ymax>603</ymax>
		</bndbox>
	</object>
	<object>
		<name>smoke</name>
		<pose>Unspecified</pose>
		<truncated>0</truncated>
		<difficult>0</difficult>
		<bndbox>
			<xmin>786</xmin>
			<ymin>604</ymin>
			<xmax>832</xmax>
			<ymax>635</ymax>
		</bndbox>
	</object>
	<object>
		<name>smoke</name>
		<pose>Unspecified</pose>
		<truncated>0</truncated>
		<difficult>0</difficult>
		<bndbox>
			<xmin>1694</xmin>
			<ymin>501</ymin>
			<xmax>1778</xmax>
			<ymax>550</ymax>
		</bndbox>
	</object>
</annotation>
