<annotation>
	<folder>smoke(1000-1599)</folder>
	<filename>001204.jpg</filename>
	<path>C:\Users\you2272631926\Desktop\smoke(1000-1599)\001204.jpg</path>
	<source>
		<database>Unknown</database>
	</source>
	<size>
		<width>467</width>
		<height>350</height>
		<depth>3</depth>
	</size>
	<segmented>0</segmented>
	<object>
		<name>smoke</name>
		<pose>Unspecified</pose>
		<truncated>0</truncated>
		<difficult>0</difficult>
		<bndbox>
			<xmin>312</xmin>
			<ymin>245</ymin>
			<xmax>359</xmax>
			<ymax>280</ymax>
		</bndbox>
	</object>
</annotation>
