<annotation>
	<folder>1</folder>
	<filename>10.jpg</filename>
	<path>C:\Users\acer\Desktop\1\10.jpg</path>
	<source>
		<database>Unknown</database>
	</source>
	<size>
		<width>360</width>
		<height>360</height>
		<depth>3</depth>
	</size>
	<segmented>0</segmented>
	<object>
		<name>smoke</name>
		<pose>Unspecified</pose>
		<truncated>0</truncated>
		<difficult>0</difficult>
		<bndbox>
			<xmin>24</xmin>
			<ymin>194</ymin>
			<xmax>105</xmax>
			<ymax>248</ymax>
		</bndbox>
	</object>
</annotation>
