<annotation>
	<folder>JPEGImages</folder>
	<filename>002265.jpg</filename>
	<path>F:\浏览器下载内容\VOC2007\JPEGImages\002265.jpg</path>
	<source>
		<database>Unknown</database>
	</source>
	<size>
		<width>370</width>
		<height>350</height>
		<depth>3</depth>
	</size>
	<segmented>0</segmented>
	<object>
		<name>smoke</name>
		<pose>Unspecified</pose>
		<truncated>0</truncated>
		<difficult>0</difficult>
		<bndbox>
			<xmin>89</xmin>
			<ymin>179</ymin>
			<xmax>110</xmax>
			<ymax>204</ymax>
		</bndbox>
	</object>
</annotation>
