<annotation>
	<folder>1</folder>
	<filename>40.jpg</filename>
	<path>C:\Users\acer\Desktop\1\40.jpg</path>
	<source>
		<database>Unknown</database>
	</source>
	<size>
		<width>400</width>
		<height>294</height>
		<depth>3</depth>
	</size>
	<segmented>0</segmented>
	<object>
		<name>smoke</name>
		<pose>Unspecified</pose>
		<truncated>0</truncated>
		<difficult>0</difficult>
		<bndbox>
			<xmin>188</xmin>
			<ymin>136</ymin>
			<xmax>239</xmax>
			<ymax>144</ymax>
		</bndbox>
	</object>
</annotation>
