<annotation>
	<folder>smoke(500-999)</folder>
	<filename>000865.jpg</filename>
	<path>C:\Users\jauok\Documents\WeChat Files\wxid_lkl5s8wk0dw822\FileStorage\File\2020-07\smoke(500-999)\000865.jpg</path>
	<source>
		<database>Unknown</database>
	</source>
	<size>
		<width>391</width>
		<height>280</height>
		<depth>3</depth>
	</size>
	<segmented>0</segmented>
	<object>
		<name>smoke</name>
		<pose>Unspecified</pose>
		<truncated>0</truncated>
		<difficult>0</difficult>
		<bndbox>
			<xmin>112</xmin>
			<ymin>66</ymin>
			<xmax>160</xmax>
			<ymax>100</ymax>
		</bndbox>
	</object>
</annotation>
