<annotation>
	<folder>smoke(1600-2099)</folder>
	<filename>001903.jpg</filename>
	<path>C:\Users\Administrator\Desktop\新建文件夹 (2)\smoke(1600-2099)\001903.jpg</path>
	<source>
		<database>Unknown</database>
	</source>
	<size>
		<width>2248</width>
		<height>1080</height>
		<depth>3</depth>
	</size>
	<segmented>0</segmented>
	<object>
		<name>smoke</name>
		<pose>Unspecified</pose>
		<truncated>0</truncated>
		<difficult>0</difficult>
		<bndbox>
			<xmin>736</xmin>
			<ymin>240</ymin>
			<xmax>784</xmax>
			<ymax>292</ymax>
		</bndbox>
	</object>
	<object>
		<name>smoke</name>
		<pose>Unspecified</pose>
		<truncated>0</truncated>
		<difficult>0</difficult>
		<bndbox>
			<xmin>751</xmin>
			<ymin>894</ymin>
			<xmax>857</xmax>
			<ymax>992</ymax>
		</bndbox>
	</object>
</annotation>
